ws_rebalancer/__init__.py
ws_rebalancer/cli.py
ws_rebalancer/portfolio.py
ws_rebalancer/position.py
ws_rebalancer/rebalancer.py
ws_rebalancer/security.py
ws_rebalancer/target_allocations_csv_reader.py
ws_rebalancer/wealthsimple_login.py
ws_rebalancer/wealthsimple_portfolio_reader.py
ws_rebalancer-2.0.0.dist-info/LICENSE
ws_rebalancer-2.0.0.dist-info/METADATA
ws_rebalancer-2.0.0.dist-info/WHEEL
ws_rebalancer-2.0.0.dist-info/entry_points.txt
ws_rebalancer-2.0.0.dist-info/RECORD
