Metadata-Version: 2.3
Name: ws-rebalancer
Version: 2.0.0
Summary: A CLI tool that helps you rebalance your WealthSimple portfolios.
License: MIT
Keywords: wealthsimple,portfolio,rebalancer,stocks
Author: Emil Maric
Author-email: emil.maric@hotmail.com
Maintainer: Emil Maric
Maintainer-email: emil.maric@hotmail.com
Requires-Python: >=3.10,<4.0
Classifier: Development Status :: 5 - Production/Stable
Classifier: Environment :: Console
Classifier: Intended Audience :: End Users/Desktop
Classifier: License :: OSI Approved :: MIT License
Classifier: Operating System :: OS Independent
Classifier: Programming Language :: Python :: 3
Classifier: Programming Language :: Python :: 3.10
Classifier: Programming Language :: Python :: 3.11
Classifier: Programming Language :: Python :: 3.12
Classifier: Programming Language :: Python :: 3.13
Classifier: Topic :: Office/Business :: Financial :: Accounting
Requires-Dist: click (>=7.1.2,<8.0.0)
Requires-Dist: wealthsimple-trade-python (>=1.1.0,<2.0.0)
Project-URL: Homepage, https://github.com/EmilMaric/ws-rebalancer
Project-URL: Repository, https://github.com/EmilMaric/ws-rebalancer
